rick_roll_detector/__init__.py
rick_roll_detector/cli.py
rick_roll_detector/image.py
rick_roll_detector/video.py
rick_roll_detector/youtube.py
rick_roll_detector/assets/training.jpg
rick_roll_detector-1.1.0.dist-info/LICENSE
rick_roll_detector-1.1.0.dist-info/METADATA
rick_roll_detector-1.1.0.dist-info/WHEEL
rick_roll_detector-1.1.0.dist-info/entry_points.txt
rick_roll_detector-1.1.0.dist-info/top_level.txt
rick_roll_detector-1.1.0.dist-info/RECORD
