Metadata-Version: 2.1
Name: rick-roll-detector
Version: 1.1.0
Summary: A Python package that detects if an image, video, or Youtube video is a Rick Roll.
Home-page: https://github.com/alexwillcode/rick-roll-detector/
Author: AlexWillCode
Author-email: alexwillcode@gmail.com
License: MIT
Platform: UNKNOWN
Classifier: Programming Language :: Python :: 3
Requires-Dist: face-recognition
Requires-Dist: opencv-python
Requires-Dist: youtube-dl
Requires-Dist: pafy
Requires-Dist: pillow
Requires-Dist: numpy
Requires-Dist: click
